llama_index/llms/deepseek/__init__.py
llama_index/llms/deepseek/base.py
llama_index/llms/deepseek/utils.py
llama_index_llms_deepseek-0.2.1.dist-info/METADATA
llama_index_llms_deepseek-0.2.1.dist-info/WHEEL
llama_index_llms_deepseek-0.2.1.dist-info/licenses/LICENSE
llama_index_llms_deepseek-0.2.1.dist-info/RECORD
